FileScape/__init__.py
FileScape/core.py
filescape-0.0.2.dist-info/METADATA
filescape-0.0.2.dist-info/WHEEL
filescape-0.0.2.dist-info/top_level.txt
filescape-0.0.2.dist-info/RECORD
